pyserval/__init__.py
pyserval/client.py
pyserval/connection.py
pyserval/exceptions.py
pyserval/keyring.py
pyserval/meshmb.py
pyserval/meshms.py
pyserval/rhizome.py
pyserval/route.py
pyserval/lowlevel/__init__.py
pyserval/lowlevel/client.py
pyserval/lowlevel/connection.py
pyserval/lowlevel/keyring.py
pyserval/lowlevel/meshmb.py
pyserval/lowlevel/meshms.py
pyserval/lowlevel/rhizome.py
pyserval/lowlevel/route.py
pyserval/lowlevel/util.py
pyserval-0.5.dist-info/LICENSE
pyserval-0.5.dist-info/METADATA
pyserval-0.5.dist-info/WHEEL
pyserval-0.5.dist-info/top_level.txt
pyserval-0.5.dist-info/zip-safe
pyserval-0.5.dist-info/RECORD
