Metadata-Version: 2.1
Name: pyserval
Version: 0.5
Summary: Python client for serval-dna REST interface
Home-page: https://github.com/umr-ds/pyserval
Author: Jonas Höchst & Markus Sommer
Author-email: msommer@informatik.uni-marburg.de
License: MIT
Project-URL: Bug Reports, https://github.com/umr-ds/pyserval/issues
Project-URL: Source, https://github.com/umr-ds/pyserval
Keywords: serval dtn
Platform: UNKNOWN
Classifier: Development Status :: 4 - Beta
Classifier: License :: OSI Approved :: MIT License
Classifier: Programming Language :: Python :: 3.6
Classifier: Programming Language :: Python :: 3.7
Classifier: Programming Language :: Python :: 3.8
Requires-Dist: requests
